vdocipher/__init__.py
vdocipher/resources/__init__.py
vdocipher/resources/annotate.py
vdocipher/resources/bandwidth.py
vdocipher/resources/ip_geo_rule.py
vdocipher/resources/license_rules.py
vdocipher/resources/otp.py
vdocipher/resources/request.py
vdocipher/resources/video.py
vdocipher/resources/routes/__init__.py
vdocipher/resources/routes/base.py
vdocipher/resources/routes/video.py
vdocipher/tests/__init__.py
vdocipher/tests/conftest.py
vdocipher/tests/test_bandwidth.py
vdocipher/tests/test_otp.py
vdocipher/tests/test_video.py
vdocipher/tests/test_video_captions.py
vdocipher.py-0.5.1.dist-info/LICENSE
vdocipher.py-0.5.1.dist-info/METADATA
vdocipher.py-0.5.1.dist-info/WHEEL
vdocipher.py-0.5.1.dist-info/top_level.txt
vdocipher.py-0.5.1.dist-info/RECORD
